scrapydo/__init__.py
scrapydo/scrapedo.py
scrapydo/scrapy.py
scrapy_scrapedo-0.1.4.dist-info/LICENSE
scrapy_scrapedo-0.1.4.dist-info/METADATA
scrapy_scrapedo-0.1.4.dist-info/WHEEL
scrapy_scrapedo-0.1.4.dist-info/top_level.txt
scrapy_scrapedo-0.1.4.dist-info/RECORD
