Metadata-Version: 2.1
Name: scrapy-scrapedo
Version: 0.1.4
Summary: Fundemantal Scrapy support for Scrape.do API
Home-page: https://github.com/scrape-do/scrapy-scrapedo
Author: Scrape.do
Author-email: hello@scrape.do
License: MIT
Project-URL: Company, https://scrape.do/?utm_source=pypi&utm_medium=scrapydo
Project-URL: Documentation, https://scrape.do/documentation/?utm_source=pypi&utm_medium=scrapydo
Project-URL: Source, https://github.com/scrape-do/scrapy-scrapedo
Classifier: Intended Audience :: Developers
Classifier: License :: OSI Approved :: MIT License
Classifier: Programming Language :: Python :: 3
Classifier: Topic :: Software Development :: Libraries
Classifier: Topic :: Software Development :: Libraries :: Python Modules
Classifier: Topic :: Internet :: WWW/HTTP
Requires-Python: >=3.8
License-File: LICENSE
Requires-Dist: scrapy
